CHANGES
COPYING
MANIFEST.in
Makefile
README
SubnetTree.cc
SubnetTree.i
SubnetTree.py
SubnetTree_wrap.cc
VERSION
patricia.c
pyproject.toml
setup.py
include/SubnetTree.h
include/patricia.h
pysubnettree.egg-info/PKG-INFO
pysubnettree.egg-info/SOURCES.txt
pysubnettree.egg-info/dependency_links.txt
pysubnettree.egg-info/top_level.txt